LICENSE
README.md
pyproject.toml
setup.cfg
setup.py
js/__init__.py
js/scripts/exists.js
js/scripts/run.js
run_js.egg-info/PKG-INFO
run_js.egg-info/SOURCES.txt
run_js.egg-info/dependency_links.txt
run_js.egg-info/top_level.txt