Metadata-Version: 2.1
Name: run-js
Version: 0.0.4
Summary: Goal: The Easiest Way to Run JavaScript in Python
Home-page: https://github.com/DanielJDufour/run-js
Author: Daniel J. Dufour
Author-email: daniel.j.dufour@gmail.com
License: UNKNOWN
Download-URL: https://github.com/DanielJDufour/run-js/tarball/download
Keywords: functional,javascript,python,package,library,universal,python3
Platform: UNKNOWN
Classifier: Programming Language :: Python :: 3
Classifier: Operating System :: OS Independent
License-File: LICENSE
